openqtsim/__init__.py
openqtsim/arrival_process.py
openqtsim/customer.py
openqtsim/mm1.py
openqtsim/mt_engine.py
openqtsim/queue.py
openqtsim/service_process.py
openqtsim/simulation.py
openqtsim-0.5.1.dist-info/AUTHORS.rst
openqtsim-0.5.1.dist-info/LICENSE.txt
openqtsim-0.5.1.dist-info/METADATA
openqtsim-0.5.1.dist-info/WHEEL
openqtsim-0.5.1.dist-info/top_level.txt
openqtsim-0.5.1.dist-info/RECORD
