Metadata-Version: 2.1
Name: openqtsim
Version: 0.5.1
Summary: OpenQTSim facilitates discrete event simulation of queues with a Kendall notation.
Home-page: https://github.com/TUDelft-CITG/OpenQTSim
Author: Mark van Koningsveld and Joris den Uijl
Author-email: m.vankoningsveld@tudelft.nl
License: mit
Keywords: Queueing Theory
Platform: any
Classifier: Development Status :: 2 - Pre-Alpha
Classifier: Intended Audience :: Developers
Classifier: Natural Language :: English
Classifier: Programming Language :: Python :: 3
Classifier: Programming Language :: Python :: 3.4
Classifier: Programming Language :: Python :: 3.5
Classifier: Programming Language :: Python :: 3.6
Classifier: Programming Language :: Python :: 3.7
License-File: LICENSE.txt
License-File: AUTHORS.rst
Requires-Dist: matplotlib
Requires-Dist: pandas
Requires-Dist: numpy
Requires-Dist: seaborn
Requires-Dist: simpy
Requires-Dist: scipy
Requires-Dist: sphinx-rtd-theme
Provides-Extra: testing
Requires-Dist: pytest ; extra == 'testing'
Requires-Dist: pytest-cov ; extra == 'testing'
